[{"MCID": "CHN071", "name": "Chondrodysplasia Punctata, Autosomal Dominant", "source_url": "https://www.malacards.org/card/chondrodysplasia_punctata_autosomal_dominant?search=Bone%20diseases", "ICD10": ["Q77.3"], "sign_or_symptoms": [], "HOP_symptoms": ["frontal bossing", "scoliosis", "cataract", "coarse hair", "epiphyseal stippling", "talipes equinovarus", "hip contracture", "sparse hair", "knee flexion contracture", "vitamin k deficiency", "moderate postnatal growth retardation", "hypoplasia of the nasal bone", "hyperkeratosis with erythema"]}, {"MCID": "AML053", "name": "Amelia, Autosomal Recessive", "source_url": "https://www.malacards.org/card/amelia_autosomal_recessive?search=Bone%20diseases", "ICD10": ["Q73.0"], "sign_or_symptoms": [], "HOP_symptoms": ["full cheeks", "micrognathia", "cryptorchidism", "non-midline cleft lip", "polyhydramnios", "hypoplasia of penis", "aplasia/hypoplasia of the lungs", "scrotal hypoplasia", "amelia involving the upper limbs", "acromelia of the lower limbs", "abnormal cardiac septum morphology", "amelia", "abnormality of the cardiac septa", "oral cleft"]}, {"MCID": "RDL031", "name": "Radial Aplasia, X-Linked", "source_url": "https://www.malacards.org/card/radial_aplasia_x_linked?search=Bone%20diseases", "ICD10": [], "sign_or_symptoms": [], "HOP_symptoms": ["hydrocephalus", "oligohydramnios", "oligodactyly", "ectrodactyly", "hypoplasia of the radius", "anal atresia", "rectovaginal fistula", "perineal fistula", "rectal atresia", "absent radius", "penile hypospadias"]}, {"MCID": "PLY182", "name": "Polydactyly, Postaxial, Type A9", "source_url": "https://www.malacards.org/card/polydactyly_postaxial_type_a9?search=Bone%20diseases", "ICD10": [], "sign_or_symptoms": [], "HOP_symptoms": []}, {"MCID": "ZYG003", "name": "Zygodactyly 1", "source_url": "https://www.malacards.org/card/zygodactyly_1?search=Bone%20diseases", "ICD10": ["Q70.3"], "sign_or_symptoms": [], "HOP_symptoms": []}, {"MCID": "INF091", "name": "Inflammatory Bowel Disease 8", "source_url": "https://www.malacards.org/card/inflammatory_bowel_disease_8?search=Bone%20diseases", "ICD10": [], "sign_or_symptoms": [], "HOP_symptoms": []}, {"MCID": "HYP497", "name": "Hyperphalangy", "source_url": "https://www.malacards.org/card/hyperphalangy?search=Bone%20diseases", "ICD10": ["Q74.8"], "sign_or_symptoms": [], "HOP_symptoms": []}, {"MCID": "PLY132", "name": "Polysyndactyly, Crossed", "source_url": "https://www.malacards.org/card/polysyndactyly_crossed?search=Bone%20diseases", "ICD10": ["Q70.4"], "sign_or_symptoms": [], "HOP_symptoms": ["finger syndactyly", "postaxial hand polydactyly", "abnormal dermatoglyphics", "depressed nasal bridge", "strabismus", "hearing abnormality", "upslanted palpebral fissure", "hypoplasia of penis", "aplasia/hypoplasia of the thumb", "abnormality of the philtrum", "abnormality of the outer ear"]}, {"MCID": "OTS010", "name": "Otosclerosis 7", "source_url": "https://www.malacards.org/card/otosclerosis_7?search=Bone%20diseases", "ICD10": [], "sign_or_symptoms": [], "HOP_symptoms": ["conductive hearing impairment", "otosclerosis", "progressive hearing impairment", "childhood onset sensorineural hearing impairment", "abnormality of the acoustic reflex"]}, {"MCID": "SPN346", "name": "Spondyloepiphyseal Dysplasia with Atlantoaxial Instability", "source_url": "https://www.malacards.org/card/spondyloepiphyseal_dysplasia_with_atlantoaxial_instability?search=Bone%20diseases", "ICD10": ["Q77.7"], "sign_or_symptoms": [], "HOP_symptoms": ["delayed skeletal maturation", "short stature", "hand muscle atrophy", "joint laxity", "respiratory failure", "limb muscle weakness", "brisk reflexes", "ankle clonus", "hemiparesis", "bulbar palsy", "tetraparesis", "lumbar hyperlordosis", "tongue fasciculations", "spondyloepiphyseal dysplasia", "hypoplasia of the capital femoral epiphysis", "spondylolysis", "atlantoaxial dislocation", "atlantoaxial instability", "spondylolisthesis at l5-s1", "os odontoideum"]}, {"MCID": "IMP019", "name": "Imperforate Oropharynx-Costovertebral Anomalies Syndrome", "source_url": "https://www.malacards.org/card/imperforate_oropharynx_costovertebral_anomalies_syndrome?search=Bone%20diseases", "ICD10": [], "sign_or_symptoms": [], "HOP_symptoms": ["low-set ears", "recurrent respiratory infections", "respiratory distress", "respiratory failure", "abnormality of the pharynx", "hemivertebrae", "missing ribs", "abnormality of the philtrum", "posteriorly rotated ears", "wide nasal bridge", "joint hyperflexibility", "epicanthus", "clinodactyly of the 5th finger", "arachnodactyly", "downslanted palpebral fissures", "overfolded helix", "polyhydramnios", "choanal atresia", "aplasia/hypoplasia of the tongue", "premature birth", "abnormality of the antitragus", "long palm", "dyspnea", "abnormal form of the vertebral bodies", "abnormality of the mouth", "abnormality of the ribs", "abnormality of the lip"]}, {"MCID": "LGB002", "name": "Leg, Absence Deformity of, with Congenital Cataract", "source_url": "https://www.malacards.org/card/leg_absence_deformity_of_with_congenital_cataract?search=Bone%20diseases", "ICD10": [], "sign_or_symptoms": [], "HOP_symptoms": ["abnormality of epiphysis morphology", "scoliosis", "hyperlordosis", "cataract", "visual impairment", "abnormality of femur morphology", "lower limb undergrowth", "anal atresia", "cranial nerve paralysis", "abnormality of the lower limb", "optic nerve dysplasia", "spondyloepiphyseal dysplasia", "developmental cataract", "progressive cataract", "duplication involving bones of the feet"]}, {"MCID": "HNT017", "name": "Hunter-Mcalpine Craniosynostosis Syndrome", "source_url": "https://www.malacards.org/card/hunter_mcalpine_craniosynostosis_syndrome?search=Bone%20diseases", "ICD10": ["Q87.0"], "sign_or_symptoms": [], "HOP_symptoms": ["intellectual disability", "short stature", "narrow mouth", "downturned corners of mouth", "craniosynostosis", "almond-shaped palpebral fissure"]}, {"MCID": "TTR010", "name": "Tetramelic Monodactyly", "source_url": "https://www.malacards.org/card/tetramelic_monodactyly?search=Bone%20diseases", "ICD10": ["Q73.8"], "sign_or_symptoms": [], "HOP_symptoms": ["split hand", "oligodactyly", "split foot", "hand monodactyly", "foot monodactyly"]}, {"MCID": "MCP034", "name": "Mucopolysaccharidosis Type 2, Attenuated Form", "source_url": "https://www.malacards.org/card/mucopolysaccharidosis_type_2_attenuated_form?search=Bone%20diseases", "ICD10": ["E76.1"], "sign_or_symptoms": [], "HOP_symptoms": []}, {"MCID": "DVL011", "name": "Developmental Dysplasia of the Hip 2", "source_url": "https://www.malacards.org/card/developmental_dysplasia_of_the_hip_2?search=Bone%20diseases", "ICD10": [], "sign_or_symptoms": ["hip pain"], "HOP_symptoms": ["hip osteoarthritis", "hip dysplasia", "coxa valga", "hip pain"]}, {"MCID": "HRR003", "name": "Herrmann Opitz Craniosynostosis", "source_url": "https://www.malacards.org/card/herrmann_opitz_craniosynostosis?search=Bone%20diseases", "ICD10": ["Q75.0"], "sign_or_symptoms": [], "HOP_symptoms": ["hypertelorism", "finger syndactyly", "short stature", "cognitive impairment", "brachycephaly", "micrognathia", "micromelia", "intrauterine growth retardation", "turricephaly", "split hand", "malar flattening", "short nose", "microtia", "cleft palate", "webbed neck", "abnormality of the upper urinary tract", "abnormality of the antihelix", "brachydactyly", "abnormality of the ribs", "convex nasal ridge", "craniosynostosis", "oligohydramnios", "abnormality of the urethra", "aplasia/hypoplasia of the lungs"]}, {"MCID": "INF161", "name": "Inflammatory Bowel Disease 28", "source_url": "https://www.malacards.org/card/inflammatory_bowel_disease_28?search=Bone%20diseases", "ICD10": [], "sign_or_symptoms": [], "HOP_symptoms": []}, {"MCID": "EHL088", "name": "Ehlers-Danlos Syndrome Type 2", "source_url": "https://www.malacards.org/card/ehlers_danlos_syndrome_type_2?search=Bone%20diseases", "ICD10": [], "sign_or_symptoms": [], "HOP_symptoms": ["joint hyperflexibility", "hyperextensible skin", "cigarette-paper scars", "pectus excavatum", "inguinal hernia", "pectus carinatum", "umbilical hernia", "pes planus", "gastroesophageal reflux", "thin skin", "varicose veins", "bruising susceptibility", "congenital diaphragmatic hernia", "aortic aneurysm", "femoral hernia", "soft skin", "hypertension", "aortic dissection", "retinal detachment", "recurrent urinary tract infections", "bladder diverticulum", "peritonitis", "abnormal oral cavity morphology"]}, {"MCID": "ECT086", "name": "Ectrodactyly-Polydactyly", "source_url": "https://www.malacards.org/card/ectrodactyly_polydactyly_2?search=Bone%20diseases", "ICD10": ["Q74.8"], "sign_or_symptoms": [], "HOP_symptoms": ["postaxial hand polydactyly", "ectrodactyly", "finger syndactyly", "abnormality of the metacarpal bones", "brachydactyly", "camptodactyly of finger", "symphalangism affecting the phalanges of the hand", "split hand", "split foot"]}, {"MCID": "OTS011", "name": "Otosclerosis 8", "source_url": "https://www.malacards.org/card/otosclerosis_8?search=Bone%20diseases", "ICD10": [], "sign_or_symptoms": [], "HOP_symptoms": ["hearing impairment", "otosclerosis"]}, {"MCID": "SYS055", "name": "Systemic Lupus Erythematosus 12", "source_url": "https://www.malacards.org/card/systemic_lupus_erythematosus_12?search=Bone%20diseases", "ICD10": [], "sign_or_symptoms": [], "HOP_symptoms": []}, {"MCID": "CRN307", "name": "Craniofrontonasal Dysplasia-Poland Anomaly Syndrome", "source_url": "https://www.malacards.org/card/craniofrontonasal_dysplasia_poland_anomaly_syndrome?search=Bone%20diseases", "ICD10": ["Q87.8"], "sign_or_symptoms": [], "HOP_symptoms": ["hypertelorism", "broad nasal tip", "craniosynostosis", "wide nose", "midline nasal groove", "aplasia/hypoplasia involving bones of the skull", "high palate", "strabismus", "aplasia/hypoplasia of the nipples", "webbed neck", "low posterior hairline", "wide mouth", "plagiocephaly", "diastasis recti", "supernumerary nipple", "sparse eyebrow", "syndactyly", "bifid uterus", "short lingual frenulum", "aplasia/hypoplasia involving the shoulder musculature", "unilateral brachydactyly", "asymmetry of the nares", "unilateral hypoplasia of pectoralis major muscle", "vertical orbital dystopia", "abnormal fingernail morphology", "abnormality of the fingernails", "abnormal reproductive system morphology"]}, {"MCID": "HRD209", "name": "Hereditary Angioedema with Normal C1inh", "source_url": "https://www.malacards.org/card/hereditary_angioedema_with_normal_c1inh?search=Bone%20diseases", "ICD10": [], "sign_or_symptoms": [], "HOP_symptoms": []}, {"MCID": "DPH002", "name": "Diaphragma Sellae Meningioma", "source_url": "https://www.malacards.org/card/diaphragma_sellae_meningioma?search=Bone%20diseases", "ICD10": [], "sign_or_symptoms": ["seizures", "headache"], "HOP_symptoms": []}, {"MCID": "CNS012", "name": "Cono-Spondylar Dysplasia", "source_url": "https://www.malacards.org/card/cono_spondylar_dysplasia?search=Bone%20diseases", "ICD10": ["Q77.7"], "sign_or_symptoms": [], "HOP_symptoms": ["muscular hypotonia", "dysostosis multiplex", "intellectual disability, severe", "cone-shaped epiphyses of the phalanges of the hand", "hypertelorism", "low-set ears", "short neck", "seizures", "failure to thrive", "scoliosis", "kyphosis", "abnormal facial shape", "anteverted nares", "epiphyseal dysplasia", "severe global developmental delay", "brachydactyly", "midface retrusion", "poor coordination", "short nail", "short 4th toe", "polyhydramnios", "partial agenesis of the corpus callosum", "short lower limbs", "short humerus", "food intolerance", "abnormality of the skeletal system"]}, {"MCID": "INT058", "name": "Intraorbital Meningioma", "source_url": "https://www.malacards.org/card/intraorbital_meningioma?search=Bone%20diseases", "ICD10": [], "sign_or_symptoms": [], "HOP_symptoms": []}, {"MCID": "EXS015", "name": "Exostoses with Anetodermia and Brachydactyly, Type E", "source_url": "https://www.malacards.org/card/exostoses_with_anetodermia_and_brachydactyly_type_e?search=Bone%20diseases", "ICD10": ["Q87.5"], "sign_or_symptoms": [], "HOP_symptoms": ["macule", "dermal atrophy", "multiple exostoses", "type e brachydactyly", "aplasia/hypoplasia of the skin"]}, {"MCID": "CHN047", "name": "Chondroectodermal Dysplasia with Night Blindness", "source_url": "https://www.malacards.org/card/chondroectodermal_dysplasia_with_night_blindness?search=Bone%20diseases", "ICD10": ["Q77.6"], "sign_or_symptoms": [], "HOP_symptoms": ["osteopenia", "hyperhidrosis", "delayed skeletal maturation", "short stature", "osteoporosis", "micrognathia", "nail dystrophy", "epiphyseal dysplasia", "platyspondyly", "hyperconvex fingernails", "otitis media", "difficulty walking", "abnormality of dental morphology", "congenital stationary night blindness", "metaphyseal dysplasia", "equinovarus deformity", "congenital onychodystrophy", "metaphyseal irregularity", "abnormality of the patella", "fractures of the long bones", "wide humerus", "talipes calcaneovarus", "hyperconvex toenail", "epiphora", "abnormal hair morphology", "onychauxis", "gait disturbance", "abnormality of the hair", "abnormality of the knee", "increased lacrimation"]}, {"MCID": "BRC090", "name": "Brachydactyly-Ectrodactyly with Fibular Aplasia or Hypoplasia", "source_url": "https://www.malacards.org/card/brachydactyly_ectrodactyly_with_fibular_aplasia_or_hypoplasia?search=Bone%20diseases", "ICD10": ["Q73.8"], "sign_or_symptoms": [], "HOP_symptoms": ["premature birth", "abnormality of the ulna", "split hand", "aplasia/hypoplasia of the fibula", "brachydactyly", "fibular aplasia", "short phalanx of finger", "split foot"]}, {"MCID": "GRN044", "name": "Granulomatous Disease, Chronic, Autosomal Dominant Type", "source_url": "https://www.malacards.org/card/granulomatous_disease_chronic_autosomal_dominant_type?search=Bone%20diseases", "ICD10": [], "sign_or_symptoms": [], "HOP_symptoms": ["granulomatosis"]}, {"MCID": "INF076", "name": "Inflammatory Bowel Disease 18", "source_url": "https://www.malacards.org/card/inflammatory_bowel_disease_18?search=Bone%20diseases", "ICD10": [], "sign_or_symptoms": [], "HOP_symptoms": []}, {"MCID": "OTS008", "name": "Otosclerosis 4", "source_url": "https://www.malacards.org/card/otosclerosis_4?search=Bone%20diseases", "ICD10": [], "sign_or_symptoms": [], "HOP_symptoms": ["otosclerosis", "mixed hearing impairment"]}, {"MCID": "CHN027", "name": "Chondrodysplasia Lethal Recessive", "source_url": "https://www.malacards.org/card/chondrodysplasia_lethal_recessive?search=Bone%20diseases", "ICD10": ["Q78.8"], "sign_or_symptoms": [], "HOP_symptoms": ["generalized osteosclerosis", "narrow chest", "short long bone", "accelerated skeletal maturation", "flared elbow metaphyses", "micrognathia", "polyhydramnios", "macroglossia", "edema", "respiratory distress", "micromelia", "limb undergrowth", "flared metaphyses (elbow)"]}, {"MCID": "HLL014", "name": "Hallux Varus and Preaxial Polysyndactyly", "source_url": "https://www.malacards.org/card/hallux_varus_and_preaxial_polysyndactyly?search=Bone%20diseases", "ICD10": ["Q74.2"], "sign_or_symptoms": [], "HOP_symptoms": ["sandal gap", "clinodactyly of the 5th finger", "preaxial hand polydactyly", "syndactyly", "hallux varus", "broad hallux"]}, {"MCID": "PST104", "name": "Postaxial Oligodactyly, Tetramelic", "source_url": "https://www.malacards.org/card/postaxial_oligodactyly_tetramelic?search=Bone%20diseases", "ICD10": ["Q73.8"], "sign_or_symptoms": [], "HOP_symptoms": ["abnormality of the metacarpal bones", "abnormality of finger", "oligodactyly", "ectrodactyly", "cone-shaped epiphysis", "postaxial hand polydactyly", "postaxial foot polydactyly", "single transverse palmar crease", "radial bowing", "postaxial oligodactyly", "partial-complete absence of 5th phalanges", "lunate-triquetral fusion", "absent fifth metatarsal", "aplasia of the 5th metacarpal"]}, {"MCID": "SYS051", "name": "Systemic Lupus Erythematosus 4", "source_url": "https://www.malacards.org/card/systemic_lupus_erythematosus_4?search=Bone%20diseases", "ICD10": [], "sign_or_symptoms": [], "HOP_symptoms": []}, {"MCID": "SYS047", "name": "Systemic Lupus Erythematosus 7", "source_url": "https://www.malacards.org/card/systemic_lupus_erythematosus_7?search=Bone%20diseases", "ICD10": [], "sign_or_symptoms": [], "HOP_symptoms": []}, {"MCID": "PSD023", "name": "Pseudo-Gaucher Disease", "source_url": "https://www.malacards.org/card/pseudo_gaucher_disease?search=Bone%20diseases", "ICD10": [], "sign_or_symptoms": [], "HOP_symptoms": []}, {"MCID": "WHB001", "name": "Wahab Syndrome", "source_url": "https://www.malacards.org/card/wahab_syndrome?search=Bone%20diseases", "ICD10": ["Q87.2"], "sign_or_symptoms": [], "HOP_symptoms": ["clinodactyly", "short palm", "short foot", "adducted thumb", "short metacarpal", "camptodactyly", "syndactyly", "short thumb", "ankylosis"]}, {"MCID": "SYN040", "name": "Synpolydactyly 3", "source_url": "https://www.malacards.org/card/synpolydactyly_3?search=Bone%20diseases", "ICD10": ["Q70.0", "Q70.2"], "sign_or_symptoms": [], "HOP_symptoms": []}, {"MCID": "MTP014", "name": "Metaphyseal Anadysplasia 2", "source_url": "https://www.malacards.org/card/metaphyseal_anadysplasia_2?search=Bone%20diseases", "ICD10": [], "sign_or_symptoms": [], "HOP_symptoms": ["bowing of the legs", "short femoral neck", "metaphyseal widening", "metaphyseal irregularity"]}, {"MCID": "AST010", "name": "Astley-Kendall Syndrome", "source_url": "https://www.malacards.org/card/astley_kendall_syndrome?search=Bone%20diseases", "ICD10": ["Q77.3"], "sign_or_symptoms": [], "HOP_symptoms": ["micromelia", "epiphyseal stippling", "disproportionate short-limb short stature", "abnormality of skull ossification"]}, {"MCID": "OSS015", "name": "Ossification Anomalies-Psychomotor Developmental Delay Syndrome", "source_url": "https://www.malacards.org/card/ossification_anomalies_psychomotor_developmental_delay_syndrome?search=Bone%20diseases", "ICD10": ["Q79.8"], "sign_or_symptoms": [], "HOP_symptoms": ["hypertelorism", "global developmental delay", "hepatomegaly", "micrognathia", "narrow chest", "elevated hepatic transaminase", "hyperostosis", "high forehead", "abnormal diaphysis morphology", "generalized hypotonia", "generalized bone demineralization", "metaphyseal widening", "dysphagia", "anteverted nares", "gastroesophageal reflux", "decreased muscle mass", "abnormal form of the vertebral bodies", "absent speech", "postnatal growth retardation", "ventriculomegaly", "thin ribs", "recurrent aspiration pneumonia", "large fontanelles", "short distal phalanx of finger", "triangular face", "delayed gross motor development", "slender long bone", "clubbing of fingers", "penile hypospadias", "short 5th finger", "shallow orbits", "triangular shaped distal phalanges of the hand", "hepatic hemangioma", "abnormality of the thorax", "abnormal bone ossification", "proptosis"]}, {"MCID": "LRS009", "name": "Larsen-Like Syndrome, Lethal Type", "source_url": "https://www.malacards.org/card/larsen_like_syndrome_lethal_type?search=Bone%20diseases", "ICD10": ["Q74.8"], "sign_or_symptoms": [], "HOP_symptoms": ["joint dislocation", "respiratory insufficiency", "laryngomalacia", "abnormality of metabolism/homeostasis", "tracheomalacia", "pulmonary hypoplasia", "abnormal cartilage matrix", "pulmonary insufficiency", "multiple joint dislocation"]}, {"MCID": "CLV003", "name": "Clivus Meningioma", "source_url": "https://www.malacards.org/card/clivus_meningioma?search=Bone%20diseases", "ICD10": [], "sign_or_symptoms": ["seizures", "headache"], "HOP_symptoms": []}, {"MCID": "PLY054", "name": "Polydactyly, Postaxial, Type A4", "source_url": "https://www.malacards.org/card/polydactyly_postaxial_type_a4?search=Bone%20diseases", "ICD10": [], "sign_or_symptoms": [], "HOP_symptoms": []}, {"MCID": "PLY053", "name": "Polydactyly, Postaxial, Type A3", "source_url": "https://www.malacards.org/card/polydactyly_postaxial_type_a3?search=Bone%20diseases", "ICD10": [], "sign_or_symptoms": [], "HOP_symptoms": []}, {"MCID": "PRV013", "name": "Periventricular Nodular Heterotopia 3", "source_url": "https://www.malacards.org/card/periventricular_nodular_heterotopia_3?search=Bone%20diseases", "ICD10": [], "sign_or_symptoms": [], "HOP_symptoms": []}, {"MCID": "MTP017", "name": "Metaphyseal Chondrodysplasia, Kaitila Type", "source_url": "https://www.malacards.org/card/metaphyseal_chondrodysplasia_kaitila_type?search=Bone%20diseases", "ICD10": [], "sign_or_symptoms": [], "HOP_symptoms": ["narrow palate", "narrow chest", "micromelia", "short toe", "motor delay", "metaphyseal chondrodysplasia", "disproportionate short-limb short stature", "convex nasal ridge", "abnormality of the respiratory system", "short metacarpal", "broad nail", "proximal femoral metaphyseal irregularity", "cone-shaped epiphyses of the phalanges of the hand", "short phalanx of finger", "limited elbow extension", "short metatarsal", "short nail", "limb undergrowth", "enlarged joints", "metaphyseal dysplasia", "hypoplastic ilia", "thoracolumbar scoliosis", "metaphyseal widening", "metaphyseal irregularity", "finger joint hypermobility", "delayed proximal femoral epiphyseal ossification"]}, {"MCID": "CXR001", "name": "Coxoauricular Syndrome", "source_url": "https://www.malacards.org/card/coxoauricular_syndrome?search=Bone%20diseases", "ICD10": ["Q87.1"], "sign_or_symptoms": [], "HOP_symptoms": ["hearing impairment", "microtia", "short stature", "micromelia", "reduced bone mineral density", "hip dislocation", "abnormality of femur morphology", "atresia of the external auditory canal", "abnormality of pelvic girdle bone morphology"]}, {"MCID": "APV001", "name": "Aapoaiv Amyloidosis", "source_url": "https://www.malacards.org/card/aapoaiv_amyloidosis?search=Bone%20diseases", "ICD10": ["E85.8"], "sign_or_symptoms": [], "HOP_symptoms": ["elevated serum creatinine", "tubular atrophy", "tubulointerstitial fibrosis", "dysuria", "glomerulosclerosis", "decreased glomerular filtration rate", "stage 3 chronic kidney disease", "chronic kidney disease", "abnormality of glycoprotein metabolism"]}, {"MCID": "CND008", "name": "Condensing Osteitis of the Clavicle", "source_url": "https://www.malacards.org/card/condensing_osteitis_of_the_clavicle?search=Bone%20diseases", "ICD10": ["M85.3"], "sign_or_symptoms": [], "HOP_symptoms": []}, {"MCID": "ATS292", "name": "Autosomal Dominant Myopia-Midfacial Retrusion-Sensorineural Hearing Loss-Rhizomelic Dysplasia Syndrome", "source_url": "https://www.malacards.org/card/autosomal_dominant_myopia_midfacial_retrusion_sensorineural_hearing_loss_rhizomelic_dysplasia_syndrome?search=Bone%20diseases", "ICD10": [], "sign_or_symptoms": [], "HOP_symptoms": ["cleft palate", "micrognathia", "narrow chest", "micromelia", "rhizomelia", "upper airway obstruction", "frontal bossing", "sensorineural hearing impairment", "glossoptosis", "brachydactyly", "midface retrusion", "proptosis", "premature birth", "hypoplastic scapulae", "femoral bowing", "short femur", "dumbbell-shaped long bone", "high myopia", "severe myopia", "metaphyseal widening"]}, {"MCID": "INF083", "name": "Inflammatory Bowel Disease 24", "source_url": "https://www.malacards.org/card/inflammatory_bowel_disease_24?search=Bone%20diseases", "ICD10": [], "sign_or_symptoms": [], "HOP_symptoms": []}, {"MCID": "INF084", "name": "Inflammatory Bowel Disease 26", "source_url": "https://www.malacards.org/card/inflammatory_bowel_disease_26?search=Bone%20diseases", "ICD10": [], "sign_or_symptoms": [], "HOP_symptoms": []}, {"MCID": "INF082", "name": "Inflammatory Bowel Disease 23", "source_url": "https://www.malacards.org/card/inflammatory_bowel_disease_23?search=Bone%20diseases", "ICD10": [], "sign_or_symptoms": [], "HOP_symptoms": []}, {"MCID": "INF085", "name": "Inflammatory Bowel Disease 27", "source_url": "https://www.malacards.org/card/inflammatory_bowel_disease_27?search=Bone%20diseases", "ICD10": [], "sign_or_symptoms": [], "HOP_symptoms": []}, {"MCID": "INF074", "name": "Inflammatory Bowel Disease 15", "source_url": "https://www.malacards.org/card/inflammatory_bowel_disease_15?search=Bone%20diseases", "ICD10": [], "sign_or_symptoms": [], "HOP_symptoms": []}, {"MCID": "INF081", "name": "Inflammatory Bowel Disease 22", "source_url": "https://www.malacards.org/card/inflammatory_bowel_disease_22?search=Bone%20diseases", "ICD10": [], "sign_or_symptoms": [], "HOP_symptoms": []}, {"MCID": "BCP001", "name": "Bicipital Tenosynovitis", "source_url": "https://www.malacards.org/card/bicipital_tenosynovitis?search=Bone%20diseases", "ICD10": [], "sign_or_symptoms": [], "HOP_symptoms": []}, {"MCID": "CRN271", "name": "Craniosynostosis, Calcification of Basal Ganglia, and Facial Dysmorphism", "source_url": "https://www.malacards.org/card/craniosynostosis_calcification_of_basal_ganglia_and_facial_dysmorphism?search=Bone%20diseases", "ICD10": ["Q87.0"], "sign_or_symptoms": [], "HOP_symptoms": ["prominent supraorbital ridges", "abnormal facial shape", "microcephaly", "prominent nasal bridge", "hypoplasia of the maxilla", "proptosis", "craniosynostosis", "basal ganglia calcification"]}, {"MCID": "EPP019", "name": "Epiphyseal Dysplasia, Multiple, with Severe Proximal Femoral Dysplasia", "source_url": "https://www.malacards.org/card/epiphyseal_dysplasia_multiple_with_severe_proximal_femoral_dysplasia?search=Bone%20diseases", "ICD10": ["Q77.3"], "sign_or_symptoms": [], "HOP_symptoms": ["genu valgum", "short stature", "arthralgia", "epiphyseal dysplasia", "platyspondyly", "abnormality of the hand", "coxa vara", "proximal femoral metaphyseal irregularity", "broad femoral neck", "short femoral neck", "arthralgia of the hip", "irregularity of vertebral bodies", "flared femoral metaphysis", "flat distal femoral epiphysis"]}, {"MCID": "ACR046", "name": "Acropectorovertebral Dysplasia F Form", "source_url": "https://www.malacards.org/card/acropectorovertebral_dysplasia_f_form?search=Bone%20diseases", "ICD10": [], "sign_or_symptoms": [], "HOP_symptoms": []}, {"MCID": "ACR027", "name": "Acrodysplasia Scoliosis", "source_url": "https://www.malacards.org/card/acrodysplasia_scoliosis?search=Bone%20diseases", "ICD10": [], "sign_or_symptoms": [], "HOP_symptoms": ["scoliosis", "brachydactyly", "spina bifida occulta", "vertebral segmentation defect"]}, {"MCID": "DNN007", "name": "Duane Anomaly-Myopathy-Scoliosis Syndrome", "source_url": "https://www.malacards.org/card/duane_anomaly_myopathy_scoliosis_syndrome?search=Bone%20diseases", "ICD10": [], "sign_or_symptoms": [], "HOP_symptoms": ["nystagmus", "muscular hypotonia", "scoliosis", "delayed skeletal maturation", "microcephaly", "visual impairment", "myopathy", "motor delay", "proportionate short stature", "duane anomaly", "strabismus"]}, {"MCID": "TRM018", "name": "Traumatic Avascular Necrosis", "source_url": "https://www.malacards.org/card/traumatic_avascular_necrosis?search=Bone%20diseases", "ICD10": ["M87.2"], "sign_or_symptoms": [], "HOP_symptoms": []}, {"MCID": "ACH028", "name": "Acheiria", "source_url": "https://www.malacards.org/card/acheiria?search=Bone%20diseases", "ICD10": ["Q71.3"], "sign_or_symptoms": [], "HOP_symptoms": []}, {"MCID": "OTS009", "name": "Otosclerosis 5", "source_url": "https://www.malacards.org/card/otosclerosis_5?search=Bone%20diseases", "ICD10": [], "sign_or_symptoms": [], "HOP_symptoms": []}, {"MCID": "TRC112", "name": "Trochlea of the Humerus, Aplasia of", "source_url": "https://www.malacards.org/card/trochlea_of_the_humerus_aplasia_of_2?search=Bone%20diseases", "ICD10": ["Q74.0"], "sign_or_symptoms": [], "HOP_symptoms": ["cleft palate", "short humerus"]}, {"MCID": "HND012", "name": "Handigodu Joint Disease", "source_url": "https://www.malacards.org/card/handigodu_joint_disease?search=Bone%20diseases", "ICD10": ["Q77.7"], "sign_or_symptoms": [], "HOP_symptoms": []}, {"MCID": "TRP023", "name": "Triphalangeal Thumbs and Dislocation of Patella", "source_url": "https://www.malacards.org/card/triphalangeal_thumbs_and_dislocation_of_patella?search=Bone%20diseases", "ICD10": ["Q74.8"], "sign_or_symptoms": [], "HOP_symptoms": ["short stature", "triphalangeal thumb", "recurrent patellar dislocation"]}, {"MCID": "TBB005", "name": "Tibia, Absence or Hypoplasia of, with Polydactyly, Retrocerebellar Arachnoid Cyst, and Other Anomalies", "source_url": "https://www.malacards.org/card/tibia_absence_or_hypoplasia_of_with_polydactyly_retrocerebellar_arachnoid_cyst_and_other_anomalies?search=Bone%20diseases", "ICD10": [], "sign_or_symptoms": [], "HOP_symptoms": ["abnormality of the thorax", "talipes equinovarus", "cleft upper lip", "postaxial foot polydactyly", "arachnoid cyst", "radial bowing", "posterior fossa cyst", "aplasia/hypoplasia of the tibia", "preaxial foot polydactyly", "choroid plexus cyst", "agenesis of the diaphragm"]}, {"MCID": "HLL012", "name": "Hallermann-Streiff-Like Syndrome", "source_url": "https://www.malacards.org/card/hallermann_streiff_like_syndrome?search=Bone%20diseases", "ICD10": ["Q87.0"], "sign_or_symptoms": [], "HOP_symptoms": []}, {"MCID": "ACQ036", "name": "Acquired Angioedema Type 2", "source_url": "https://www.malacards.org/card/acquired_angioedema_type_2?search=Bone%20diseases", "ICD10": ["T78.3"], "sign_or_symptoms": [], "HOP_symptoms": []}, {"MCID": "MXD037", "name": "Mixed Cryoglobulinemia Type Iii", "source_url": "https://www.malacards.org/card/mixed_cryoglobulinemia_type_iii?search=Bone%20diseases", "ICD10": ["D89.1"], "sign_or_symptoms": [], "HOP_symptoms": []}, {"MCID": "SYS048", "name": "Systemic Lupus Erythematosus 8", "source_url": "https://www.malacards.org/card/systemic_lupus_erythematosus_8?search=Bone%20diseases", "ICD10": [], "sign_or_symptoms": [], "HOP_symptoms": []}, {"MCID": "SYS067", "name": "Systemic Lupus Erythematosus 15", "source_url": "https://www.malacards.org/card/systemic_lupus_erythematosus_15?search=Bone%20diseases", "ICD10": [], "sign_or_symptoms": [], "HOP_symptoms": []}, {"MCID": "SCL058", "name": "Scoliosis, Isolated 2", "source_url": "https://www.malacards.org/card/scoliosis_isolated_2?search=Bone%20diseases", "ICD10": [], "sign_or_symptoms": [], "HOP_symptoms": []}, {"MCID": "SYS052", "name": "Systemic Lupus Erythematosus 13", "source_url": "https://www.malacards.org/card/systemic_lupus_erythematosus_13?search=Bone%20diseases", "ICD10": [], "sign_or_symptoms": [], "HOP_symptoms": []}, {"MCID": "SYS045", "name": "Systemic Lupus Erythematosus 14", "source_url": "https://www.malacards.org/card/systemic_lupus_erythematosus_14?search=Bone%20diseases", "ICD10": [], "sign_or_symptoms": [], "HOP_symptoms": []}, {"MCID": "VRN007", "name": "Variant Abeta2m Amyloidosis", "source_url": "https://www.malacards.org/card/variant_abeta2m_amyloidosis?search=Bone%20diseases", "ICD10": ["E85.1"], "sign_or_symptoms": [], "HOP_symptoms": ["bowel incontinence", "malabsorption", "weight loss", "keratoconjunctivitis sicca", "vertigo", "xerostomia", "gastrointestinal hemorrhage", "chronic diarrhea", "orthostatic hypotension due to autonomic dysfunction", "chronic constipation", "intermittent diarrhea", "autonomic bladder dysfunction", "gastrointestinal dysmotility", "chronic axonal neuropathy", "constipation", "autonomic dysregulation"]}, {"MCID": "CRN204", "name": "Craniofacial Conodysplasia", "source_url": "https://www.malacards.org/card/craniofacial_conodysplasia?search=Bone%20diseases", "ICD10": ["Q87.5"], "sign_or_symptoms": [], "HOP_symptoms": ["hydrocephalus", "cone-shaped epiphyses of the phalanges of the hand", "craniofacial dysostosis", "spinal cord compression", "abnormality of the face"]}, {"MCID": "PRM222", "name": "Primary Polyarteritis Nodosa", "source_url": "https://www.malacards.org/card/primary_polyarteritis_nodosa?search=Bone%20diseases", "ICD10": ["M30.0"], "sign_or_symptoms": [], "HOP_symptoms": []}, {"MCID": "ISC019", "name": "Ischiovertebral Syndrome", "source_url": "https://www.malacards.org/card/ischiovertebral_syndrome?search=Bone%20diseases", "ICD10": ["Q77.8"], "sign_or_symptoms": [], "HOP_symptoms": []}, {"MCID": "MTP033", "name": "Metaphyseal Enchondromatosis with D-2-Hydroxyglutaric Aciduria", "source_url": "https://www.malacards.org/card/metaphyseal_enchondromatosis_with_d_2_hydroxyglutaric_aciduria?search=Bone%20diseases", "ICD10": [], "sign_or_symptoms": [], "HOP_symptoms": []}, {"MCID": "B3G001", "name": "B3galt6-Related Spondylodysplastic Ehlers-Danlos Syndrome", "source_url": "https://www.malacards.org/card/b3galt6_related_spondylodysplastic_ehlers_danlos_syndrome?search=Bone%20diseases", "ICD10": [], "sign_or_symptoms": [], "HOP_symptoms": []}, {"MCID": "EPP018", "name": "Epiphyseal Dysplasia, Multiple, with Miniepiphyses", "source_url": "https://www.malacards.org/card/epiphyseal_dysplasia_multiple_with_miniepiphyses?search=Bone%20diseases", "ICD10": ["Q77.3"], "sign_or_symptoms": [], "HOP_symptoms": ["short stature", "epiphyseal dysplasia", "genu varum", "lumbar hyperlordosis", "patellar hypoplasia", "generalized joint laxity", "broad femoral neck", "short femoral neck", "irregular patellae"]}, {"MCID": "IGG010", "name": "Igg4-Related Aortitis", "source_url": "https://www.malacards.org/card/igg4_related_aortitis?search=Bone%20diseases", "ICD10": ["I77.6"], "sign_or_symptoms": [], "HOP_symptoms": []}, {"MCID": "INF052", "name": "Infantile Scoliosis", "source_url": "https://www.malacards.org/card/infantile_scoliosis?search=Bone%20diseases", "ICD10": [], "sign_or_symptoms": [], "HOP_symptoms": []}, {"MCID": "ANK018", "name": "Ankyloblepharon Filiforme Adnatum-Imperforate Anus Syndrome", "source_url": "https://www.malacards.org/card/ankyloblepharon_filiforme_adnatum_imperforate_anus_syndrome?search=Bone%20diseases", "ICD10": ["Q87.8"], "sign_or_symptoms": [], "HOP_symptoms": ["cryptorchidism", "ankyloblepharon", "reduced number of teeth", "cleft palate", "non-midline cleft lip"]}, {"MCID": "IDP040", "name": "Idiopathic Eosinophilic Myositis", "source_url": "https://www.malacards.org/card/idiopathic_eosinophilic_myositis?search=Bone%20diseases", "ICD10": ["M60.8"], "sign_or_symptoms": [], "HOP_symptoms": []}, {"MCID": "SYM014", "name": "Symbrachydactyly of Hands and Feet", "source_url": "https://www.malacards.org/card/symbrachydactyly_of_hands_and_feet?search=Bone%20diseases", "ICD10": ["Q73.8"], "sign_or_symptoms": [], "HOP_symptoms": ["maternal diabetes", "abnormality of the humeroulnar joint", "scoliosis", "abnormality of the ulna", "vertebral segmentation defect", "aplasia/hypoplasia of the thumb", "aplasia/hypoplasia of the radius", "abnormality of the humerus"]}, {"MCID": "FBR007", "name": "Fibroosseous Pseudotumor of Digits", "source_url": "https://www.malacards.org/card/fibroosseous_pseudotumor_of_digits?search=Bone%20diseases", "ICD10": [], "sign_or_symptoms": [], "HOP_symptoms": []}, {"MCID": "MTC143", "name": "Mitochondrial Dna Depletion Syndrome 12b", "source_url": "https://www.malacards.org/card/mitochondrial_dna_depletion_syndrome_12b?search=Bone%20diseases", "ICD10": [], "sign_or_symptoms": [], "HOP_symptoms": []}, {"MCID": "MTC142", "name": "Mitochondrial Dna Depletion Syndrome 12a", "source_url": "https://www.malacards.org/card/mitochondrial_dna_depletion_syndrome_12a?search=Bone%20diseases", "ICD10": [], "sign_or_symptoms": [], "HOP_symptoms": []}, {"MCID": "CRN087", "name": "Craniomicromelic Syndrome", "source_url": "https://www.malacards.org/card/craniomicromelic_syndrome?search=Bone%20diseases", "ICD10": ["Q87.0"], "sign_or_symptoms": [], "HOP_symptoms": []}, {"MCID": "ANT021", "name": "Anterior Foramen Magnum Meningioma", "source_url": "https://www.malacards.org/card/anterior_foramen_magnum_meningioma?search=Bone%20diseases", "ICD10": [], "sign_or_symptoms": ["seizures", "headache"], "HOP_symptoms": []}, {"MCID": "BST002", "name": "Baastrup's Syndrome", "source_url": "https://www.malacards.org/card/baastrups_syndrome?search=Bone%20diseases", "ICD10": ["M48.2", "M48.20"], "sign_or_symptoms": [], "HOP_symptoms": []}, {"MCID": "PRM233", "name": "Primary Cutaneous Plasmacytosis", "source_url": "https://www.malacards.org/card/primary_cutaneous_plasmacytosis?search=Bone%20diseases", "ICD10": ["L98.6"], "sign_or_symptoms": [], "HOP_symptoms": []}]